imio.helpers-1.3.10-py3.12-nspkg.pth
imio/helpers/__init__.py
imio/helpers/adapters.py
imio/helpers/appy_pod.html
imio/helpers/appy_pod.py
imio/helpers/barcode.py
imio/helpers/batching.py
imio/helpers/cache.py
imio/helpers/catalog.py
imio/helpers/configure.zcml
imio/helpers/content.py
imio/helpers/converters.py
imio/helpers/date.py
imio/helpers/emailer.py
imio/helpers/events.py
imio/helpers/events.zcml
imio/helpers/imageNotFound.jpg
imio/helpers/interfaces.py
imio/helpers/patches.py
imio/helpers/path.py
imio/helpers/pdf.py
imio/helpers/profiles.zcml
imio/helpers/ram.py
imio/helpers/security.py
imio/helpers/setup.py
imio/helpers/setuphandlers.py
imio/helpers/test_helpers.py
imio/helpers/testing.py
imio/helpers/testing.zcml
imio/helpers/transmogrifier.py
imio/helpers/utils.py
imio/helpers/vocabularies.py
imio/helpers/workflow.py
imio/helpers/ws.py
imio/helpers/xhtml.py
imio/helpers/browser/__init__.py
imio/helpers/browser/configure.zcml
imio/helpers/browser/container.pt
imio/helpers/browser/content.pt
imio/helpers/browser/folder_listing.pt
imio/helpers/browser/folder_listing_table.pt
imio/helpers/browser/ramcache.pt
imio/helpers/browser/registry_icons.pt
imio/helpers/browser/views.py
imio/helpers/browser/static/helpers.js
imio/helpers/browser/static/listings.js
imio/helpers/fancytree/__init__.py
imio/helpers/fancytree/configure.zcml
imio/helpers/fancytree/fancytree.js
imio/helpers/fancytree/fancytree.pt
imio/helpers/fancytree/views.py
imio/helpers/locales/imio.helpers.pot
imio/helpers/locales/manual.pot
imio/helpers/locales/update.sh
imio/helpers/locales/fr/LC_MESSAGES/imio.helpers.po
imio/helpers/profiles/base/browserlayer.xml
imio/helpers/profiles/base/metadata.xml
imio/helpers/profiles/plone4/jsregistry.xml
imio/helpers/profiles/plone4/metadata.xml
imio/helpers/profiles/plone6/metadata.xml
imio/helpers/profiles/plone6/registry.xml
imio/helpers/profiles/testing/metadata.xml
imio/helpers/profiles/testing/types.xml
imio/helpers/profiles/testing/types/testingtype.xml
imio_helpers-1.3.10.dist-info/METADATA
imio_helpers-1.3.10.dist-info/WHEEL
imio_helpers-1.3.10.dist-info/entry_points.txt
imio_helpers-1.3.10.dist-info/namespace_packages.txt
imio_helpers-1.3.10.dist-info/top_level.txt
imio_helpers-1.3.10.dist-info/RECORD
