Metadata-Version: 2.4
Name: imio.helpers
Version: 1.3.10
Summary: Various helper methods for development.
Home-page: https://github.com/imio/imio.helpers
Download-URL: https://pypi.org/project/imio.helpers
Author: Simon Delcourt
Author-email: simon.delcourt@imio.be
License: GPL
Keywords: plone helpers utils dev imio
Classifier: Development Status :: 5 - Production/Stable
Classifier: Environment :: Web Environment
Classifier: Framework :: Plone
Classifier: Framework :: Plone :: 4.3
Classifier: Framework :: Plone :: 6.0
Classifier: Framework :: Plone :: 6.1
Classifier: License :: OSI Approved :: GNU General Public License v2 (GPLv2)
Classifier: Operating System :: OS Independent
Classifier: Programming Language :: Python
Classifier: Programming Language :: Python :: 2.7
Classifier: Programming Language :: Python :: 3.9
Classifier: Programming Language :: Python :: 3.10
Classifier: Programming Language :: Python :: 3.11
Classifier: Programming Language :: Python :: 3.12
Classifier: Programming Language :: Python :: 3.13
Requires-Dist: collective.fingerpointing
Requires-Dist: collective.monkeypatcher
Requires-Dist: future>=0.18.2
Requires-Dist: imio.pyutils>=1.1.1
Requires-Dist: natsort
Requires-Dist: pathlib2; python_version < "3"
Requires-Dist: plone.api>1.9.1
Requires-Dist: plone.app.intid
Requires-Dist: plone.app.relationfield
Requires-Dist: plone.dexterity
Requires-Dist: setuptools
Requires-Dist: six
Requires-Dist: Plone
Requires-Dist: z3c.unconfigure
Provides-Extra: test
Requires-Dist: collective.behavior.talcondition; extra == "test"
Requires-Dist: collective.MockMailHost; extra == "test"
Requires-Dist: ftw.labels; python_version < "3" and extra == "test"
Requires-Dist: plone.app.dexterity; extra == "test"
Requires-Dist: plone.app.testing; extra == "test"
Provides-Extra: pdf
Requires-Dist: PyPDF2; extra == "pdf"
Requires-Dist: reportlab; extra == "pdf"
Provides-Extra: lxml
Requires-Dist: cssselect<1.2; python_version == "2.7" and extra == "lxml"
Dynamic: author
Dynamic: author-email
Dynamic: classifier
Dynamic: description
Dynamic: download-url
Dynamic: home-page
Dynamic: keywords
Dynamic: license
Dynamic: provides-extra
Dynamic: requires-dist
Dynamic: summary
